HTBClient/__init__.py
HTBClient/__main__.py
HTBClient/assigned.py
HTBClient/client.py
HTBClient/machine.py
HTBClient/machinedetails.py
HTBClient/own.py
HTBClient/spawned.py
HTBClient/terminating.py
HTBClient/models/__init__.py
HTBClient/models/assigned.py
HTBClient/models/machine.py
HTBClient/models/machinedetails.py
HTBClient/models/own.py
HTBClient/models/spawned.py
HTBClient/models/terminating.py
HTBClient-0.4.0.dist-info/LICENSE
HTBClient-0.4.0.dist-info/METADATA
HTBClient-0.4.0.dist-info/WHEEL
HTBClient-0.4.0.dist-info/entry_points.txt
HTBClient-0.4.0.dist-info/top_level.txt
HTBClient-0.4.0.dist-info/RECORD
