Metadata-Version: 2.1
Name: HTBClient
Version: 0.4.0
Summary: A command line client and library to interact with the hackthebox.eu website
Home-page: https://github.com/BGrewell/HTBClient
Author: Benjamin Grewell
Author-email: bgrewelldev@gmail.com
License: UNKNOWN
Platform: UNKNOWN
Classifier: Development Status :: 4 - Beta
Classifier: Programming Language :: Python :: 3
Classifier: License :: OSI Approved :: Apache Software License
Classifier: Operating System :: POSIX :: Linux
Classifier: Natural Language :: English
Classifier: Environment :: Console
Classifier: Intended Audience :: Information Technology
Requires-Python: >=3.6
